setup.cfg
setup.py
django_simple_jsonschema/__init__.py
django_simple_jsonschema.egg-info/PKG-INFO
django_simple_jsonschema.egg-info/SOURCES.txt
django_simple_jsonschema.egg-info/dependency_links.txt
django_simple_jsonschema.egg-info/requires.txt
django_simple_jsonschema.egg-info/top_level.txt
django_simple_jsonschema/management/__init__.py
django_simple_jsonschema/management/commands/__init__.py
django_simple_jsonschema/management/commands/check_schema.py