Metadata-Version: 1.1
Name: django-simple-jsonschema
Version: 0.0.5
Summary: django-simple-jsonschema is middleware for integrating django and jsonschema. 
Home-page: https://github.com/38elements/django-simple-jsonschema
Author: 38elements
Author-email: UNKNOWN
License: MIT License
Keywords: django jsonschema
Platform: UNKNOWN
Classifier: Development Status :: 3 - Alpha
Classifier: Framework :: Django
Classifier: Programming Language :: Python :: 3 :: Only
Classifier: License :: OSI Approved :: MIT License
Classifier: Intended Audience :: Developers
